cdn/__init__.py
cdn/cdn_analysis.py
cdn/data_preprocess.py
cdn/evaluation_1.py
cdn/main_computation.py
cdn/model_config.py
cdn/validation_truncation_1.py
cdn_fmri-0.0.2.dist-info/METADATA
cdn_fmri-0.0.2.dist-info/RECORD
cdn_fmri-0.0.2.dist-info/WHEEL
cdn_fmri-0.0.2.dist-info/top_level.txt
