Metadata-Version: 2.1
Name: cdn-fmri
Version: 0.0.2
Summary: Implementations of Causal Dynamic Network Analysis of fMRI
Home-page: https://github.com/xuefeicao/cdn
Author: Xuefei Cao, Xi Luo, Bjorn Sandstede
Author-email: xcstf01@gmail.com
License: UNKNOWN
Platform: UNKNOWN
Requires-Dist: matplotlib (>=1.5.3)
Requires-Dist: numpy (>=1.11.1)
Requires-Dist: scipy (>=0.19.0)
Requires-Dist: six (>=1.10.0)
Requires-Dist: scikit-learn (>=0.18.1)
